s3tests_pytest/__init__.py
s3tests_pytest/conftest.py
s3tests_pytest/main.py
s3tests_pytest/functional/__init__.py
s3tests_pytest/functional/policy.py
s3tests_pytest/functional/s3_sigv4.py
s3tests_pytest/tests/__init__.py
s3tests_pytest/tests/conftest.py
s3tests_pytest/tests/test_s3_acl_v.py
s3tests_pytest/tests/test_s3_bucket_v.py
s3tests_pytest/tests/test_s3_cors_x.py
s3tests_pytest/tests/test_s3_encryption_x.py
s3tests_pytest/tests/test_s3_headers_x.py
s3tests_pytest/tests/test_s3_lifecycle_v.py
s3tests_pytest/tests/test_s3_metadata_x.py
s3tests_pytest/tests/test_s3_multipart_upload_v.py
s3tests_pytest/tests/test_s3_object_lock_x.py
s3tests_pytest/tests/test_s3_object_v.py
s3tests_pytest/tests/test_s3_policy_acl_mixin_v.py
s3tests_pytest/tests/test_s3_policy_v.py
s3tests_pytest/tests/test_s3_samples_from_awsdocs_v.py
s3tests_pytest/tests/test_s3_scenarios_x.py
s3tests_pytest/tests/test_s3_tagging_policy_mixin_v.py
s3tests_pytest/tests/test_s3_tagging_v.py
s3tests_pytest/tests/test_s3_versioning_v.py
s3tests_pytest-1.0.0.dist-info/LICENSE
s3tests_pytest-1.0.0.dist-info/METADATA
s3tests_pytest-1.0.0.dist-info/WHEEL
s3tests_pytest-1.0.0.dist-info/top_level.txt
s3tests_pytest-1.0.0.dist-info/RECORD
